pychromecast/__init__.py
pychromecast/config.py
pychromecast/const.py
pychromecast/dial.py
pychromecast/discovery.py
pychromecast/error.py
pychromecast/models.py
pychromecast/py.typed
pychromecast/quick_play.py
pychromecast/response_handler.py
pychromecast/socket_client.py
pychromecast/controllers/__init__.py
pychromecast/controllers/bbciplayer.py
pychromecast/controllers/bbcsounds.py
pychromecast/controllers/bubbleupnp.py
pychromecast/controllers/dashcast.py
pychromecast/controllers/heartbeat.py
pychromecast/controllers/homeassistant.py
pychromecast/controllers/homeassistant_media.py
pychromecast/controllers/media.py
pychromecast/controllers/multizone.py
pychromecast/controllers/nrkradio.py
pychromecast/controllers/nrktv.py
pychromecast/controllers/plex.py
pychromecast/controllers/receiver.py
pychromecast/controllers/shaka.py
pychromecast/controllers/supla.py
pychromecast/controllers/yleareena.py
pychromecast/controllers/youtube.py
pychromecast/generated/authority_keys_pb2.py
pychromecast/generated/authority_keys_pb2.pyi
pychromecast/generated/cast_channel_pb2.py
pychromecast/generated/cast_channel_pb2.pyi
pychromecast/generated/logging_pb2.py
pychromecast/generated/logging_pb2.pyi
pychromecast/generated/readme.txt
pychromecast-14.0.9.dist-info/licenses/LICENSE
pychromecast-14.0.9.dist-info/METADATA
pychromecast-14.0.9.dist-info/WHEEL
pychromecast-14.0.9.dist-info/top_level.txt
pychromecast-14.0.9.dist-info/RECORD
