Metadata-Version: 2.4
Name: PyChromecast
Version: 14.0.9
Summary: Python module to talk to Google Chromecast.
Author-email: Paulus Schoutsen <paulus@paulusschoutsen.nl>
License: MIT
Project-URL: Homepage, https://github.com/home-assistant-libs/pychromecast
Platform: any
Classifier: Intended Audience :: Developers
Classifier: License :: OSI Approved :: MIT License
Classifier: Operating System :: OS Independent
Classifier: Programming Language :: Python
Classifier: Programming Language :: Python :: 3
Classifier: Topic :: Software Development :: Libraries :: Python Modules
Classifier: Typing :: Typed
Requires-Python: >=3.11.0
License-File: LICENSE
Requires-Dist: protobuf>=4.25.1
Requires-Dist: zeroconf>=0.25.1
Requires-Dist: casttube>=0.2.0
Dynamic: license-file
